soap2json/__init__.py
soap2json/adapters.py
soap2json/session.py
soap2json-0.1.6.dist-info/METADATA
soap2json-0.1.6.dist-info/WHEEL
soap2json-0.1.6.dist-info/top_level.txt
soap2json-0.1.6.dist-info/RECORD
